extremevariantfilter/__init__.py
extremevariantfilter/variant_filtering.py
extremevariantfilter-0.0a4.data/scripts/apply_filter
extremevariantfilter-0.0a4.data/scripts/train_model
extremevariantfilter-0.0a4.dist-info/LICENSE
extremevariantfilter-0.0a4.dist-info/METADATA
extremevariantfilter-0.0a4.dist-info/WHEEL
extremevariantfilter-0.0a4.dist-info/top_level.txt
extremevariantfilter-0.0a4.dist-info/RECORD
