Metadata-Version: 2.1
Name: extremevariantfilter
Version: 0.0a4
Summary: A set of tools to aid in the identification of false positive variants in Variant Call Files.
Home-page: https://github.com/stLFR/extremevariantfilter
Author: Complete Genomics
Author-email: eanderson@genomics.cn
License: UNKNOWN
Platform: UNKNOWN
Classifier: Development Status :: 3 - Alpha
Classifier: Programming Language :: Python :: 2.7
Classifier: Intended Audience :: Science/Research
Classifier: Topic :: Scientific/Engineering :: Bio-Informatics
Requires-Dist: scikit-learn
Requires-Dist: numpy
Requires-Dist: pandas
Requires-Dist: xgboost
Requires-Dist: docopt
